LICENSE
MANIFEST.in
README.md
setup.cfg
setup.py
tap_nikabot/__init__.py
tap_nikabot/client.py
tap_nikabot/errors.py
tap_nikabot/replication_method.py
tap_nikabot/typing.py
tap_nikabot.egg-info/PKG-INFO
tap_nikabot.egg-info/SOURCES.txt
tap_nikabot.egg-info/dependency_links.txt
tap_nikabot.egg-info/entry_points.txt
tap_nikabot.egg-info/requires.txt
tap_nikabot.egg-info/top_level.txt
tap_nikabot/streams/__init__.py
tap_nikabot/streams/groups.py
tap_nikabot/streams/projects.py
tap_nikabot/streams/records.py
tap_nikabot/streams/roles.py
tap_nikabot/streams/stream.py
tap_nikabot/streams/teams.py
tap_nikabot/streams/users.py